tenxagent/__init__.py
tenxagent/agent.py
tenxagent/history.py
tenxagent/models.py
tenxagent/schemas.py
tenxagent/tools.py
tenxagent/utils.py
tenxagent-0.1.20.dist-info/licenses/LICENSE.txt
tenxagent-0.1.20.dist-info/METADATA
tenxagent-0.1.20.dist-info/WHEEL
tenxagent-0.1.20.dist-info/top_level.txt
tenxagent-0.1.20.dist-info/RECORD
