Metadata-Version: 2.4
Name: tenxagent
Version: 0.1.20
Summary: A flexible, Pydantic-powered library for building AI agents.
Author-email: Andrew Bain <andrew.d.bain@gmail.com>
Project-URL: Homepage, https://github.com/andrewbain/tenxagent
Project-URL: Issues, https://github.com/andrewbain/tenxagentagent/issues
Classifier: Programming Language :: Python :: 3
Classifier: License :: OSI Approved :: MIT License
Classifier: Operating System :: OS Independent
Classifier: Intended Audience :: Developers
Classifier: Topic :: Scientific/Engineering :: Artificial Intelligence
Requires-Python: >=3.8
License-File: LICENSE.txt
Requires-Dist: pydantic
Requires-Dist: httpx
Requires-Dist: openai
Requires-Dist: tiktoken
Requires-Dist: python-dotenv
Provides-Extra: mongo
Requires-Dist: motor; extra == "mongo"
Dynamic: license-file
